bootstrap_builder/__init__.py
bootstrap_builder/bootstrap_node.py
bootstrap_builder/node.py
bootstrap_builder/page.py
bootstrap_builder-0.0.5.dist-info/METADATA
bootstrap_builder-0.0.5.dist-info/WHEEL
bootstrap_builder-0.0.5.dist-info/top_level.txt
bootstrap_builder-0.0.5.dist-info/RECORD
