Metadata-Version: 2.1
Name: bootstrap-builder
Version: 0.0.5
Summary: A small small package I use to turn some objects into Bootstrap HTML
Home-page: https://github.com/4Kaylum/BootstrapHTMLBuilder
Author: Callum Bartlett
Author-email: bartlett.c@outlook.com
License: UNKNOWN
Platform: UNKNOWN
Classifier: Programming Language :: Python :: 3
Classifier: Operating System :: OS Independent
Requires-Python: >=3.5
